_mediainfo_cffi.abi3.so
libmediainfo_cffi/__init__.py
.libs_mediainfo_cffi/libplds4-eda05ca2.so
.libs_mediainfo_cffi/libnspr4-0d962fa9.so
.libs_mediainfo_cffi/libnssutil3-753d1456.so
.libs_mediainfo_cffi/libssl3-9b66d973.so
.libs_mediainfo_cffi/libldap-2-ee840ad3.4.so.2.10.3
.libs_mediainfo_cffi/libkrb5support-2ce1fd50.so.0.1
.libs_mediainfo_cffi/libsasl2-03ca2345.so.2.0.23
.libs_mediainfo_cffi/libplc4-df17d39f.so
.libs_mediainfo_cffi/libkeyutils-68db41cc.so.1.3
.libs_mediainfo_cffi/liblber-2-bc719061.4.so.2.10.3
.libs_mediainfo_cffi/libkrb5-7e4170ab.so.3.3
.libs_mediainfo_cffi/libssh2-868e6f95.so.1.0.1
.libs_mediainfo_cffi/libsmime3-25a87ed6.so
.libs_mediainfo_cffi/libidn-0c8ed23f.so.11.6.1
.libs_mediainfo_cffi/libcurl-ef2f586a.so.4.1.1
.libs_mediainfo_cffi/libcrypto-a94305d7.so.1.0.1e
.libs_mediainfo_cffi/libmediainfo-58765d74.so.0.1904.0
.libs_mediainfo_cffi/libssl-cce1538c.so.1.0.1e
.libs_mediainfo_cffi/libz-eb09ad1d.so.1.2.3
.libs_mediainfo_cffi/libk5crypto-ab4ddf4c.so.3.1
.libs_mediainfo_cffi/libgssapi_krb5-bb73e344.so.2.2
.libs_mediainfo_cffi/libtinyxml2-3cbd2d61.so.1.0.11
.libs_mediainfo_cffi/libnss3-c1288e50.so
.libs_mediainfo_cffi/libselinux-d72a37e2.so.1
.libs_mediainfo_cffi/libzen-62fd7e94.so.0.4.37
.libs_mediainfo_cffi/libcom_err-f79b9776.so.2.1
libmediainfo_cffi-2.1.5.dist-info/WHEEL
libmediainfo_cffi-2.1.5.dist-info/top_level.txt
libmediainfo_cffi-2.1.5.dist-info/METADATA
libmediainfo_cffi-2.1.5.dist-info/RECORD
