Metadata-Version: 2.1
Name: libmediainfo-cffi
Version: 2.1.5
Summary: CFFI interface for libmediainfo
Home-page: https://github.com/strychnide/libmediainfo_cffi
Author: Alessandro Cerruti
Author-email: thereap3r97@gmail.com
License: MIT
Project-URL: Source, https://github.com/strychnide/libmediainfo_cffi
Project-URL: Issues, https://github.com/strychnide/libmediainfo_cffi/issues
Platform: UNKNOWN
Requires-Python: >=3.5
Provides-Extra: dev
Requires-Dist: cffi
Provides-Extra: dev
Requires-Dist: flake8; extra == 'dev'
Requires-Dist: flake8-import-order; extra == 'dev'
Requires-Dist: flake8-quotes; extra == 'dev'
Requires-Dist: flake8-bugbear; extra == 'dev'
